[
    {
        "text": "QuinnWuest: so",
        "annotation": []
    },
    {
        "text": "QuinnWuest: :shrug:",
        "annotation": []
    },
    {
        "text": "QuinnWuest: even though i didnt mention 1 at all",
        "annotation": []
    },
    {
        "text": "QuinnWuest: entire game",
        "annotation": []
    },
    {
        "text": "ImAnAnt: get outta here noot",
        "annotation": []
    },
    {
        "text": "SingSing: Thx noot",
        "annotation": []
    },
    {
        "text": "QuinnWuest: ant dms",
        "annotation": []
    },
    {
        "text": "QuinnWuest: rq",
        "annotation": []
    },
    {
        "text": "ImAnAnt: I puke of u noot",
        "annotation": []
    },
    {
        "text": "Inflated: apologies qw. i didnt see 15 conf claim",
        "annotation": []
    },
    {
        "text": "Inflated: im watching billions",
        "annotation": []
    },
    {
        "text": "ImAnAnt: shut up noot we are td",
        "annotation": []
    },
    {
        "text": "ImAnAnt: 123 td out",
        "annotation": []
    },
    {
        "text": "SingSing: i was trying to read the fascist articles",
        "annotation": []
    },
    {
        "text": "SingSing: to see if they were different",
        "annotation": []
    },
    {
        "text": "SingSing: but all 3 were the same",
        "annotation": []
    },
    {
        "text": "ImAnAnt: I only read liberal articles",
        "annotation": []
    },
    {
        "text": "QuinnWuest: inflated",
        "annotation": []
    },
    {
        "text": "QuinnWuest: just dm me who you are bruh",
        "annotation": []
    },
    {
        "text": "Inflated: im a no name",
        "annotation": []
    },
    {
        "text": "ImAnAnt: noot",
        "annotation": []
    },
    {
        "text": "ImAnAnt: I have a question for you sir",
        "annotation": []
    },
    {
        "text": "SingSing: thx for overclaiming for me",
        "annotation": []
    },
    {
        "text": "QuinnWuest: i claimed my cards btw",
        "annotation": []
    },
    {
        "text": "ImAnAnt: I have an interview tomorrow, is it true that you should aim for 90 seconds or less on behavioral questions",
        "annotation": []
    },
    {
        "text": "ImAnAnt: and let them ask the follow ups",
        "annotation": []
    },
    {
        "text": "RichRobby: i dont know",
        "annotation": []
    },
    {
        "text": "ImAnAnt: I ramble too much",
        "annotation": []
    },
    {
        "text": "RichRobby: i just roll with vibes",
        "annotation": []
    },
    {
        "text": "RichRobby: obviouslty when u look like me",
        "annotation": []
    },
    {
        "text": "RichRobby: u get away with a bit more",
        "annotation": []
    },
    {
        "text": "RichRobby: but 4 ur a chad urself",
        "annotation": [
            "Friendship/Liking"
        ]
    },
    {
        "text": "ImAnAnt: so good 3",
        "annotation": []
    },
    {
        "text": "AyBendito: 1x",
        "annotation": []
    },
    {
        "text": "ImAnAnt: ok I'll give it a good try then",
        "annotation": []
    },
    {
        "text": "CuckKania: oh fuck I found",
        "annotation": []
    },
    {
        "text": "QuinnWuest: 73 the dream?",
        "annotation": []
    },
    {
        "text": "CuckKania: im amazing",
        "annotation": []
    },
    {
        "text": "ImAnAnt: oh yeah im all on that",
        "annotation": []
    },
    {
        "text": "ImAnAnt: but im a certified yapper",
        "annotation": []
    },
    {
        "text": "SingSing: did i draw 3 reds on a fas",
        "annotation": []
    },
    {
        "text": "ImAnAnt: :feelsbadman: ",
        "annotation": []
    },
    {
        "text": "ImAnAnt: I was on my leetcode and neetcode too",
        "annotation": []
    },
    {
        "text": "ImAnAnt: I inverted the binary tree",
        "annotation": []
    },
    {
        "text": "QuinnWuest: damn!",
        "annotation": []
    },
    {
        "text": "QuinnWuest: they neined Quinn Wuest!",
        "annotation": []
    },
    {
        "text": "Inflated: which company ",
        "annotation": []
    },
    {
        "text": "ImAnAnt: can't say here 6",
        "annotation": []
    },
    {
        "text": "ImAnAnt: the haters are on the prowl",
        "annotation": []
    },
    {
        "text": "Inflated: lol",
        "annotation": []
    },
    {
        "text": "CuckKania: I would pick 17",
        "annotation": []
    },
    {
        "text": "AyBendito: 3",
        "annotation": []
    },
    {
        "text": "ImAnAnt: not a famous one tho",
        "annotation": []
    },
    {
        "text": "AyBendito: was 37 really rbb?",
        "annotation": []
    },
    {
        "text": "SingSing: 3 overclaimed for me, so pick him",
        "annotation": [
            "Authority"
        ]
    },
    {
        "text": "ImAnAnt: pick me aybendito",
        "annotation": []
    },
    {
        "text": "RichRobby: no it was RRB",
        "annotation": []
    },
    {
        "text": "Inflated: as long as you dont get sys design i think in most companies you are chilling",
        "annotation": []
    },
    {
        "text": "SingSing: ok 3 is hitler",
        "annotation": []
    },
    {
        "text": "AyBendito: For real?",
        "annotation": []
    },
    {
        "text": "AyBendito: I\u2019ll just 14",
        "annotation": []
    },
    {
        "text": "ImAnAnt: I can make a UML diagram @6 my education hasn't been wasted",
        "annotation": []
    },
    {
        "text": "ImAnAnt: sharding tho",
        "annotation": []
    },
    {
        "text": "ImAnAnt: shiet ",
        "annotation": []
    },
    {
        "text": "AyBendito: should blue ",
        "annotation": []
    },
    {
        "text": "AyBendito: or my reads off",
        "annotation": []
    },
    {
        "text": "ImAnAnt: not the reads",
        "annotation": []
    },
    {
        "text": "AyBendito: 3 you was just here ",
        "annotation": []
    },
    {
        "text": "SingSing: guy tells me to stop playing tft",
        "annotation": []
    },
    {
        "text": "AyBendito: Wow",
        "annotation": []
    },
    {
        "text": "ImAnAnt: so good 1",
        "annotation": []
    },
    {
        "text": "AyBendito: 5b?",
        "annotation": []
    },
    {
        "text": "Inflated: lol i had a sys design interview and they asked me something that needed a graph db",
        "annotation": []
    },
    {
        "text": "Inflated: i got cooked",
        "annotation": []
    },
    {
        "text": "ImAnAnt: ew",
        "annotation": []
    },
    {
        "text": "ImAnAnt: what the fuck",
        "annotation": []
    },
    {
        "text": "AyBendito: I was nervous I\u2019d look dumb if it confed lol",
        "annotation": []
    },
    {
        "text": "ImAnAnt: bruh im tryna be an intern they arent hitting me with that shit",
        "annotation": []
    },
    {
        "text": "SingSing: so 56 jad 37",
        "annotation": []
    },
    {
        "text": "ImAnAnt: glassdoor tells me they ask their fulltime engineers array questions",
        "annotation": []
    },
    {
        "text": "RichRobby: i mean 4s never gona conf theer if fascist",
        "annotation": []
    },
    {
        "text": "Inflated: lmao",
        "annotation": []
    },
    {
        "text": "SingSing: so 56 aren't regfas on 37 liblib",
        "annotation": []
    },
    {
        "text": "Inflated: my friend at amazon got asked 2sum",
        "annotation": []
    },
    {
        "text": "ImAnAnt: some sliding window some hashap",
        "annotation": []
    },
    {
        "text": "ImAnAnt: BRO WHAT",
        "annotation": []
    },
    {
        "text": "SingSing: 1 can drop on 14 to make me look worse",
        "annotation": []
    },
    {
        "text": "Inflated: she got the job",
        "annotation": []
    },
    {
        "text": "SingSing: so 1 is probably libhit too",
        "annotation": []
    },
    {
        "text": "ImAnAnt: dude please ask me 2sum",
        "annotation": []
    },
    {
        "text": "SingSing: so that means 347 has hitler",
        "annotation": []
    },
    {
        "text": "SingSing: im so good",
        "annotation": []
    },
    {
        "text": "ImAnAnt: I can make noot proud and solve 3sum",
        "annotation": []
    },
    {
        "text": "RichRobby: im just gonna stay out of govs",
        "annotation": []
    },
    {
        "text": "ImAnAnt: then make 3 proud and have a 3sum",
        "annotation": []
    },
    {
        "text": "RichRobby: i solve 3sums",
        "annotation": []
    },
    {
        "text": "RichRobby: every night",
        "annotation": []
    },
    {
        "text": "RichRobby: so good 4",
        "annotation": []
    },
    {
        "text": "QuinnWuest: well 4 picking 7 odds are 0",
        "annotation": []
    },
    {
        "text": "QuinnWuest: yeah",
        "annotation": []
    },
    {
        "text": "ImAnAnt: so good 3",
        "annotation": []
    },
    {
        "text": "QuinnWuest: unlucky",
        "annotation": []
    },
    {
        "text": "SingSing: no i just said random words",
        "annotation": []
    },
    {
        "text": "RichRobby: how 14 got picked over 13 is wild",
        "annotation": []
    },
    {
        "text": "QuinnWuest: ^",
        "annotation": []
    },
    {
        "text": "RichRobby: time for some reds",
        "annotation": []
    },
    {
        "text": "RichRobby: try?",
        "annotation": []
    },
    {
        "text": "CuckKania: i honeslty dont know what 2 is up to ",
        "annotation": []
    },
    {
        "text": "SingSing: play blue so i can get free win?",
        "annotation": []
    },
    {
        "text": "SingSing: ok",
        "annotation": []
    },
    {
        "text": "RichRobby: i just wait for SE",
        "annotation": []
    },
    {
        "text": "ImAnAnt: oh good try by me",
        "annotation": []
    },
    {
        "text": "RichRobby: inv me",
        "annotation": []
    },
    {
        "text": "RichRobby: gogogo",
        "annotation": []
    },
    {
        "text": "QuinnWuest: well we can ask 1",
        "annotation": []
    },
    {
        "text": "ImAnAnt: sure 3",
        "annotation": []
    },
    {
        "text": "QuinnWuest: why he went 14 over 13",
        "annotation": []
    },
    {
        "text": "QuinnWuest: lets ask 1",
        "annotation": []
    },
    {
        "text": "SingSing: can u inv me",
        "annotation": []
    },
    {
        "text": "RichRobby: gimme dat SE now",
        "annotation": []
    },
    {
        "text": "QuinnWuest: hey 1",
        "annotation": []
    },
    {
        "text": "SingSing: sad",
        "annotation": []
    },
    {
        "text": "ImAnAnt: hello there",
        "annotation": []
    },
    {
        "text": "QuinnWuest: why did you go 14 over 13?",
        "annotation": []
    },
    {
        "text": "RichRobby: here i am",
        "annotation": []
    },
    {
        "text": "ImAnAnt: my good friend richrobby is lib",
        "annotation": [
            "Friendship/Liking"
        ]
    },
    {
        "text": "RichRobby: thats a great question isnt it",
        "annotation": []
    },
    {
        "text": "ImAnAnt: its so back",
        "annotation": []
    },
    {
        "text": "AyBendito: Why not inv me",
        "annotation": []
    },
    {
        "text": "ImAnAnt: @6 was she applying for an internship or smth",
        "annotation": []
    },
    {
        "text": "QuinnWuest: 1 stop dodging question",
        "annotation": []
    },
    {
        "text": "QuinnWuest: 1",
        "annotation": []
    },
    {
        "text": "ImAnAnt: when was this",
        "annotation": []
    },
    {
        "text": "QuinnWuest: why did you go 14 over 13",
        "annotation": []
    },
    {
        "text": "QuinnWuest: when 37 blued",
        "annotation": []
    },
    {
        "text": "ImAnAnt: 2sum is crazy",
        "annotation": []
    },
    {
        "text": "QuinnWuest: and 4 did nothing",
        "annotation": []
    },
    {
        "text": "AyBendito: 3 said rbb then reclaim ",
        "annotation": []
    },
    {
        "text": "AyBendito: to rrb",
        "annotation": []
    },
    {
        "text": "Inflated: this was during covid",
        "annotation": []
    },
    {
        "text": "ImAnAnt: hm",
        "annotation": []
    },
    {
        "text": "Inflated: ok bendithrow",
        "annotation": []
    },
    {
        "text": "Inflated: lets run it",
        "annotation": []
    },
    {
        "text": "RichRobby: i sense not lib lib here",
        "annotation": []
    },
    {
        "text": "RichRobby: my dick tells me so",
        "annotation": []
    },
    {
        "text": "RichRobby: i have preference",
        "annotation": []
    },
    {
        "text": "RichRobby: oh dear.",
        "annotation": []
    },
    {
        "text": "AyBendito: Hm",
        "annotation": []
    },
    {
        "text": "AyBendito: well I\u2019m lib",
        "annotation": []
    },
    {
        "text": "RichRobby: well u should be picking in 1/6 always",
        "annotation": [
            "Consistency"
        ]
    },
    {
        "text": "RichRobby: BUUUUUBS",
        "annotation": []
    },
    {
        "text": "ImAnAnt: bubbles hello!",
        "annotation": []
    },
    {
        "text": "ImAnAnt: :yaypanda: ",
        "annotation": []
    },
    {
        "text": "SingSing: im the perfect defense against 3f if ur lib quinn",
        "annotation": [
            "Authority"
        ]
    },
    {
        "text": "SingSing: quinn think about it",
        "annotation": []
    },
    {
        "text": "AyBendito: 7 my answer is genuine btw",
        "annotation": []
    },
    {
        "text": "SingSing: if 3 is lib",
        "annotation": []
    },
    {
        "text": "SingSing: 56 jas 37",
        "annotation": []
    },
    {
        "text": "SingSing: when they can nein to 51",
        "annotation": []
    },
    {
        "text": "ImAnAnt: the goat olong",
        "annotation": []
    },
    {
        "text": "ImAnAnt: bubbles im not playin :sadhug: ",
        "annotation": []
    },
    {
        "text": "SingSing: so if 37 liblib 56 are lib hit",
        "annotation": []
    },
    {
        "text": "SingSing: so that means",
        "annotation": []
    },
    {
        "text": "SingSing: 14 are the regfas",
        "annotation": []
    },
    {
        "text": "SingSing: palying 4thblue",
        "annotation": []
    },
    {
        "text": "ImAnAnt: yes always olong",
        "annotation": []
    },
    {
        "text": "CuckKania: well quinn ",
        "annotation": []
    },
    {
        "text": "SingSing: so i feel like 37 not liblib",
        "annotation": []
    },
    {
        "text": "AyBendito: Lol 2",
        "annotation": []
    },
    {
        "text": "ImAnAnt: im focusing on job stuff here :cry: ",
        "annotation": []
    },
    {
        "text": "AyBendito: fuck off",
        "annotation": []
    },
    {
        "text": "Inflated: 2's onto nothing <3",
        "annotation": []
    },
    {
        "text": "RichRobby: so good to focus here",
        "annotation": []
    },
    {
        "text": "AyBendito: im most lib",
        "annotation": []
    },
    {
        "text": "Inflated: here",
        "annotation": []
    },
    {
        "text": "AyBendito: on table",
        "annotation": []
    },
    {
        "text": "SingSing: did u read",
        "annotation": []
    },
    {
        "text": "SingSing: my chat",
        "annotation": []
    },
    {
        "text": "SingSing: or no",
        "annotation": []
    },
    {
        "text": "SingSing: i said",
        "annotation": []
    },
    {
        "text": "QuinnWuest: yes i did",
        "annotation": []
    },
    {
        "text": "SingSing: IF",
        "annotation": []
    },
    {
        "text": "Inflated: no",
        "annotation": []
    },
    {
        "text": "QuinnWuest: ref",
        "annotation": []
    },
    {
        "text": "ImAnAnt: whats 7 thinkin about so hard bro",
        "annotation": []
    },
    {
        "text": "SingSing: i said IF",
        "annotation": []
    },
    {
        "text": "ImAnAnt: pick someone in 13",
        "annotation": []
    },
    {
        "text": "AyBendito: im the most lib ",
        "annotation": []
    },
    {
        "text": "SingSing: and 1 got offended",
        "annotation": []
    },
    {
        "text": "CuckKania: 1 two games ago was jaing random govs in 347 lines instead of taking 12 that passed 5th blue",
        "annotation": [
            "Consistency"
        ]
    },
    {
        "text": "ImAnAnt: bubbles :libhappyhug: ",
        "annotation": []
    },
    {
        "text": "SingSing: i said the word IF <x> then 14 are ff playgn 4th blue WHICH IS UNLIKELY",
        "annotation": []
    },
    {
        "text": "SingSing: then 1 got offended",
        "annotation": []
    },
    {
        "text": "CuckKania: I think 1 is acapble of picking 4 instead of 37",
        "annotation": []
    },
    {
        "text": "SingSing: 145h moment",
        "annotation": []
    },
    {
        "text": "RichRobby: this is a resignation pick",
        "annotation": []
    },
    {
        "text": "RichRobby: btw",
        "annotation": []
    },
    {
        "text": "RichRobby: we all agree yes",
        "annotation": [
            "Social Validation"
        ]
    },
    {
        "text": "ImAnAnt: yes ofc",
        "annotation": [
            "Social Validation"
        ]
    },
    {
        "text": "SingSing: robby isn't wrong",
        "annotation": []
    },
    {
        "text": "RichRobby: XD",
        "annotation": []
    },
    {
        "text": "AyBendito: Yea ",
        "annotation": []
    },
    {
        "text": "ImAnAnt: good try 7",
        "annotation": []
    },
    {
        "text": "RichRobby: hhave some fucking shame",
        "annotation": []
    },
    {
        "text": "ImAnAnt: lets td once",
        "annotation": []
    },
    {
        "text": "RichRobby: go topdeck to me ",
        "annotation": []
    },
    {
        "text": "ImAnAnt: to 3",
        "annotation": []
    },
    {
        "text": "QuinnWuest: well",
        "annotation": []
    },
    {
        "text": "QuinnWuest: memes",
        "annotation": []
    },
    {
        "text": "QuinnWuest: imagine if 1 went 13 over 14",
        "annotation": []
    },
    {
        "text": "Inflated: good luck mr 2",
        "annotation": []
    },
    {
        "text": "AyBendito: WHY ",
        "annotation": []
    },
    {
        "text": "Inflated: we shall try to do a good se",
        "annotation": []
    },
    {
        "text": "Inflated: here",
        "annotation": []
    },
    {
        "text": "RichRobby: wym why",
        "annotation": []
    },
    {
        "text": "RichRobby: this isnt acceptable",
        "annotation": []
    },
    {
        "text": "RichRobby: no",
        "annotation": []
    },
    {
        "text": "SingSing: is 7 outign fas?",
        "annotation": []
    },
    {
        "text": "AyBendito: ARE YOU",
        "annotation": []
    },
    {
        "text": "RichRobby: there is no good SE",
        "annotation": []
    },
    {
        "text": "RichRobby: 7 outed fascist",
        "annotation": []
    },
    {
        "text": "RichRobby: 7 coulda picked",
        "annotation": []
    },
    {
        "text": "QuinnWuest: im lib bruh",
        "annotation": []
    },
    {
        "text": "RichRobby: anyone at the table",
        "annotation": []
    },
    {
        "text": "AyBendito: FASSIKG ME",
        "annotation": []
    },
    {
        "text": "SingSing: u can pick 71",
        "annotation": []
    },
    {
        "text": "SingSing: if ur lib",
        "annotation": []
    },
    {
        "text": "RichRobby: 34 openly neined to 7",
        "annotation": []
    },
    {
        "text": "RichRobby: over jaing 61",
        "annotation": []
    },
    {
        "text": "AyBendito: FOR READS",
        "annotation": []
    },
    {
        "text": "QuinnWuest: i know i can pick 71",
        "annotation": []
    },
    {
        "text": "RichRobby: and 7 picked 3",
        "annotation": []
    },
    {
        "text": "ImAnAnt: wym \"we should do a good se\" lol",
        "annotation": []
    },
    {
        "text": "QuinnWuest: but 1s pick on 4 was",
        "annotation": []
    },
    {
        "text": "RichRobby: 7 coulda picked 71 or 76",
        "annotation": []
    },
    {
        "text": "QuinnWuest: so ass ",
        "annotation": []
    },
    {
        "text": "AyBendito: I HAD READ",
        "annotation": []
    },
    {
        "text": "QuinnWuest: man",
        "annotation": []
    },
    {
        "text": "ImAnAnt: 3 is outed a liberal",
        "annotation": []
    },
    {
        "text": "RichRobby: and picked 3",
        "annotation": []
    },
    {
        "text": "ImAnAnt: 7 is outed fascist",
        "annotation": []
    },
    {
        "text": "RichRobby: i cant bel ockedo ut",
        "annotation": []
    },
    {
        "text": "AyBendito: sorry for caps",
        "annotation": []
    },
    {
        "text": "CuckKania: well I will play open hands ",
        "annotation": []
    },
    {
        "text": "RichRobby: any gov was spuposed to play and SE 3 on reds ",
        "annotation": []
    },
    {
        "text": "SingSing: 7 cant even linecall",
        "annotation": []
    },
    {
        "text": "RichRobby: TD once to richard",
        "annotation": []
    },
    {
        "text": "AyBendito:  I should not caps",
        "annotation": []
    },
    {
        "text": "QuinnWuest: ok 2",
        "annotation": []
    },
    {
        "text": "QuinnWuest: ur lib",
        "annotation": []
    },
    {
        "text": "QuinnWuest: 34x",
        "annotation": []
    },
    {
        "text": "SingSing: eat my ass quinn",
        "annotation": []
    },
    {
        "text": "QuinnWuest: x is probably in 56",
        "annotation": []
    },
    {
        "text": "SingSing: u lib me",
        "annotation": []
    },
    {
        "text": "AyBendito:  I\u2019m lib ",
        "annotation": []
    },
    {
        "text": "SingSing: the red pres",
        "annotation": []
    },
    {
        "text": "QuinnWuest: yeah i lib you now",
        "annotation": [
            "Reciprocation"
        ]
    },
    {
        "text": "SingSing: over others?",
        "annotation": []
    },
    {
        "text": "SingSing: XDDDD",
        "annotation": []
    },
    {
        "text": "CuckKania: I dislike 2's chat after 14 pick ",
        "annotation": []
    },
    {
        "text": "SingSing: gtfo",
        "annotation": []
    },
    {
        "text": "RichRobby: \"x is in 56\"",
        "annotation": []
    },
    {
        "text": "QuinnWuest: ?????????",
        "annotation": []
    },
    {
        "text": "AyBendito: lets SE 1",
        "annotation": []
    },
    {
        "text": "RichRobby: think about thiw",
        "annotation": []
    },
    {
        "text": "RichRobby: this",
        "annotation": []
    },
    {
        "text": "AyBendito: 7",
        "annotation": []
    },
    {
        "text": "AyBendito: why even73?",
        "annotation": []
    },
    {
        "text": "AyBendito: 2 called 73 libs",
        "annotation": []
    },
    {
        "text": "SingSing: 73 has no logic to it",
        "annotation": []
    },
    {
        "text": "ImAnAnt: I mean 7 is openfascist why are people asking them questions",
        "annotation": []
    },
    {
        "text": "ImAnAnt: 347 or se 3",
        "annotation": []
    },
    {
        "text": "RichRobby: 7 is calling a fascist in 5/6",
        "annotation": []
    },
    {
        "text": "QuinnWuest: bc ur pick on 14 was ass",
        "annotation": []
    },
    {
        "text": "AyBendito: lib lib",
        "annotation": []
    },
    {
        "text": "RichRobby: 345 346",
        "annotation": []
    },
    {
        "text": "SingSing: ok 1 has no reading comprehension",
        "annotation": []
    },
    {
        "text": "RichRobby: when 61 was neined for 7",
        "annotation": []
    },
    {
        "text": "AyBendito: DUD",
        "annotation": []
    },
    {
        "text": "RichRobby: by 3 and 4",
        "annotation": []
    },
    {
        "text": "AyBendito: EITS",
        "annotation": []
    },
    {
        "text": "RichRobby: XD",
        "annotation": []
    },
    {
        "text": "AyBendito: A RWAD",
        "annotation": []
    },
    {
        "text": "AyBendito: READ",
        "annotation": []
    },
    {
        "text": "RichRobby: 1 if u keep",
        "annotation": []
    },
    {
        "text": "SingSing: i said if 73 are libs then 14 are the two regfas from my pov",
        "annotation": []
    },
    {
        "text": "RichRobby: asking for SE",
        "annotation": []
    },
    {
        "text": "RichRobby: ur not getting it",
        "annotation": []
    },
    {
        "text": "AyBendito: imfg",
        "annotation": []
    },
    {
        "text": "RichRobby: 3 is resigned to ",
        "annotation": []
    },
    {
        "text": "QuinnWuest: idc what ur reasoning was",
        "annotation": []
    },
    {
        "text": "AyBendito: punish me",
        "annotation": []
    },
    {
        "text": "QuinnWuest: ur pick was shit",
        "annotation": []
    },
    {
        "text": "QuinnWuest: 1",
        "annotation": []
    },
    {
        "text": "RichRobby: ok",
        "annotation": []
    },
    {
        "text": "RichRobby: 1 is punished",
        "annotation": []
    },
    {
        "text": "RichRobby: we are TDing once to 3",
        "annotation": []
    },
    {
        "text": "CuckKania: 2 is making se in 16",
        "annotation": []
    },
    {
        "text": "ImAnAnt: who cares about punishment",
        "annotation": []
    },
    {
        "text": "Inflated: ok that means im sed",
        "annotation": []
    },
    {
        "text": "ImAnAnt: it's 3s game",
        "annotation": []
    },
    {
        "text": "Inflated: no",
        "annotation": []
    },
    {
        "text": "RichRobby: no",
        "annotation": []
    },
    {
        "text": "Inflated: 3 sed 6",
        "annotation": []
    },
    {
        "text": "ImAnAnt: 2 acknowledged it",
        "annotation": []
    },
    {
        "text": "RichRobby: there is no se",
        "annotation": []
    },
    {
        "text": "RichRobby: its my gmae",
        "annotation": []
    },
    {
        "text": "ImAnAnt: 3 did not se 6",
        "annotation": []
    },
    {
        "text": "SingSing: the sad thing is i thought 3 could be fas but after 73 i cant consider 34x lines that seriously anymore",
        "annotation": []
    },
    {
        "text": "RichRobby: i cant be invd lib and taken out ",
        "annotation": []
    },
    {
        "text": "Inflated: calling 1 fas",
        "annotation": []
    },
    {
        "text": "AyBendito: I mean",
        "annotation": []
    },
    {
        "text": "AyBendito: 37 wasn\u2019t ll",
        "annotation": []
    },
    {
        "text": "QuinnWuest: idk ref",
        "annotation": []
    },
    {
        "text": "QuinnWuest: just keep being stubborn i guess",
        "annotation": []
    },
    {
        "text": "RichRobby: ok 2 if u think that then blame 7 for pickign 3 when 3 didnt ask to be picked?",
        "annotation": []
    },
    {
        "text": "RichRobby: so TD to 3?",
        "annotation": []
    },
    {
        "text": "SingSing: says the guy that picked 73",
        "annotation": []
    },
    {
        "text": "ImAnAnt: bruh gogo",
        "annotation": []
    },
    {
        "text": "Inflated: timer",
        "annotation": []
    },
    {
        "text": "QuinnWuest: ofc i pick 73",
        "annotation": []
    },
    {
        "text": "AyBendito: i did everything correctly ",
        "annotation": []
    },
    {
        "text": "RichRobby: 3 didnt even ask to bei n gov",
        "annotation": []
    },
    {
        "text": "QuinnWuest: gives me most info",
        "annotation": []
    },
    {
        "text": "AyBendito: if",
        "annotation": []
    },
    {
        "text": "ImAnAnt: 7 ur outed",
        "annotation": []
    },
    {
        "text": "ImAnAnt: throw the se",
        "annotation": []
    },
    {
        "text": "CuckKania: 2 pick se in 16",
        "annotation": []
    },
    {
        "text": "AyBendito: my libs ",
        "annotation": []
    },
    {
        "text": "SingSing: ligma balls",
        "annotation": []
    },
    {
        "text": "RichRobby: we are topdecking to 3",
        "annotation": []
    },
    {
        "text": "AyBendito: cant find me",
        "annotation": []
    },
    {
        "text": "SingSing: no if 3 is fas 7 threw the game",
        "annotation": []
    },
    {
        "text": "QuinnWuest: ref i know ur lib",
        "annotation": []
    },
    {
        "text": "RichRobby: i dont care what ur role is 1",
        "annotation": []
    },
    {
        "text": "QuinnWuest: and just stubborn now",
        "annotation": []
    },
    {
        "text": "SingSing: td ",
        "annotation": []
    },
    {
        "text": "RichRobby: ur not acknolwedging",
        "annotation": []
    },
    {
        "text": "RichRobby: 7 is confirmed lib",
        "annotation": []
    },
    {
        "text": "QuinnWuest: saying im fas for 73 pick",
        "annotation": []
    },
    {
        "text": "RichRobby: fas*",
        "annotation": []
    },
    {
        "text": "RichRobby: im confimred lib.",
        "annotation": [
            "Authority"
        ]
    },
    {
        "text": "CuckKania: just 16. 2 DIDNT MAKE SEjust 16. 2 DIDNT MAKE SEjust 16. 2 DIDNT MAKE SEjust 16. 2 DIDNT MAKE SEjust 16. 2 DIDNT MAKE SE",
        "annotation": []
    },
    {
        "text": "RichRobby: nice freudian slip here",
        "annotation": []
    },
    {
        "text": "QuinnWuest: when i pick it bc i dont think 134 is a line",
        "annotation": []
    },
    {
        "text": "RichRobby: ok TD to 3 ",
        "annotation": []
    },
    {
        "text": "SingSing: im not stubborn i canlt let you conf the inved lib as fas ",
        "annotation": []
    },
    {
        "text": "ImAnAnt: 2 has libbed 3 and 7 is outed fascist",
        "annotation": []
    },
    {
        "text": "ImAnAnt: can we move",
        "annotation": []
    },
    {
        "text": "ImAnAnt: pls",
        "annotation": []
    },
    {
        "text": "RichRobby: 1 if u stall for more than 20 more seconds",
        "annotation": [
            "Scarcity"
        ]
    },
    {
        "text": "QuinnWuest: ok 2",
        "annotation": []
    },
    {
        "text": "CuckKania: 2 didnt make se. he is treated as fascist from now on ",
        "annotation": []
    },
    {
        "text": "RichRobby: i will never involve u in this game",
        "annotation": []
    },
    {
        "text": "QuinnWuest: im lib in no worlds why?",
        "annotation": []
    },
    {
        "text": "QuinnWuest: bc i pick 73?",
        "annotation": []
    },
    {
        "text": "QuinnWuest: or what",
        "annotation": []
    },
    {
        "text": "QuinnWuest: when 1s pick on 4 was ass",
        "annotation": []
    },
    {
        "text": "QuinnWuest: and i didnt think 134",
        "annotation": []
    },
    {
        "text": "QuinnWuest: ?",
        "annotation": []
    },
    {
        "text": "SingSing: yes because ur supposed to pick 7x and on finding blue and getting confed u se 3",
        "annotation": []
    },
    {
        "text": "CuckKania: 1 pick 6",
        "annotation": []
    },
    {
        "text": "SingSing: now u can make up blues to throw se",
        "annotation": []
    },
    {
        "text": "AyBendito: Jaing ",
        "annotation": []
    },
    {
        "text": "ImAnAnt: lets nein to the liberal in seat 3",
        "annotation": []
    },
    {
        "text": "QuinnWuest: none of 126 se'd each other",
        "annotation": []
    },
    {
        "text": "RichRobby: anyone who jas this government is confimred fascims",
        "annotation": [
            "Authority"
        ]
    },
    {
        "text": "SingSing: imagine calling it 234",
        "annotation": []
    },
    {
        "text": "CuckKania: 2 who do yo ulike in 16",
        "annotation": []
    },
    {
        "text": "AyBendito: No ty",
        "annotation": []
    },
    {
        "text": "AyBendito: move",
        "annotation": []
    },
    {
        "text": "CuckKania: it was up to 2 to se in 16",
        "annotation": []
    },
    {
        "text": "CuckKania: 6 asked 2",
        "annotation": []
    },
    {
        "text": "CuckKania: 5 asked 2",
        "annotation": []
    },
    {
        "text": "RichRobby: k ill just call 157",
        "annotation": []
    },
    {
        "text": "CuckKania: 2 was dodging the qwuestions ",
        "annotation": []
    },
    {
        "text": "RichRobby: 1 is punished",
        "annotation": []
    },
    {
        "text": "RichRobby: for eternity",
        "annotation": []
    },
    {
        "text": "AyBendito: I\u2019m passing ",
        "annotation": []
    },
    {
        "text": "RichRobby: this isnt acceptable",
        "annotation": []
    },
    {
        "text": "SingSing: either SE me or i nein to 3",
        "annotation": []
    },
    {
        "text": "RichRobby: nope",
        "annotation": []
    },
    {
        "text": "RichRobby: this is fucking unacceptable",
        "annotation": []
    },
    {
        "text": "CuckKania: XD",
        "annotation": []
    },
    {
        "text": "QuinnWuest: its not my decision",
        "annotation": []
    },
    {
        "text": "SingSing: i'm not placing 1 or 6 above myself",
        "annotation": []
    },
    {
        "text": "Inflated: i mean if 37 both call 2 lib",
        "annotation": []
    },
    {
        "text": "RichRobby: 7 avoids 1 and picks 3 ",
        "annotation": []
    },
    {
        "text": "Inflated: ja 2",
        "annotation": []
    },
    {
        "text": "SingSing: in any universe",
        "annotation": []
    },
    {
        "text": "RichRobby: now ses 1",
        "annotation": []
    },
    {
        "text": "QuinnWuest: ofc 6 silent votes",
        "annotation": []
    },
    {
        "text": "ImAnAnt: what?",
        "annotation": []
    },
    {
        "text": "QuinnWuest: ok",
        "annotation": []
    },
    {
        "text": "ImAnAnt: when did 3 lib 2",
        "annotation": []
    },
    {
        "text": "AyBendito: I\u2019m passing move ty",
        "annotation": []
    },
    {
        "text": "SingSing: call 234 then",
        "annotation": []
    },
    {
        "text": "RichRobby: 2 just pick 6",
        "annotation": []
    },
    {
        "text": "CuckKania: XDDDD",
        "annotation": []
    },
    {
        "text": "AyBendito: LOL",
        "annotation": []
    },
    {
        "text": "Inflated: 3 told 1 is fascist",
        "annotation": []
    },
    {
        "text": "RichRobby: i punish the fuck out of 1",
        "annotation": []
    },
    {
        "text": "ImAnAnt: how is 3 not getting se",
        "annotation": []
    },
    {
        "text": "SingSing: if it's 34x with 7 lib i dont care",
        "annotation": []
    },
    {
        "text": "RichRobby: for the rest of the gmae",
        "annotation": []
    },
    {
        "text": "Inflated: so 2 is lib",
        "annotation": []
    },
    {
        "text": "ImAnAnt: no it can be 257",
        "annotation": []
    },
    {
        "text": "SingSing: about this game",
        "annotation": []
    },
    {
        "text": "RichRobby: the way 1 pis playing is not acceptable",
        "annotation": []
    },
    {
        "text": "RichRobby: idc if its 257",
        "annotation": []
    },
    {
        "text": "ImAnAnt: 3 is confirmed liberal",
        "annotation": []
    },
    {
        "text": "RichRobby: 1 can learn",
        "annotation": []
    },
    {
        "text": "ImAnAnt: bro",
        "annotation": []
    },
    {
        "text": "CuckKania: why is 3 geting sed ",
        "annotation": []
    },
    {
        "text": "RichRobby: 1 will be learning from this ",
        "annotation": []
    },
    {
        "text": "ImAnAnt: 6 is a cnh",
        "annotation": []
    },
    {
        "text": "RichRobby: if hes liberal",
        "annotation": []
    },
    {
        "text": "ImAnAnt: and 3 is outed lib",
        "annotation": []
    },
    {
        "text": "CuckKania: no l",
        "annotation": []
    },
    {
        "text": "ImAnAnt: 2 tried to se 3 and 3 didnt get it ",
        "annotation": []
    },
    {
        "text": "AyBendito: what did I do wrong",
        "annotation": []
    },
    {
        "text": "RichRobby: and learn to resign to 3 when 7 outs fascist on a resignation pick",
        "annotation": []
    },
    {
        "text": "SingSing: 73 resigns to 3",
        "annotation": []
    },
    {
        "text": "RichRobby: and has an option of 71",
        "annotation": []
    },
    {
        "text": "ImAnAnt: and yall gon ja 2 > 3?",
        "annotation": []
    },
    {
        "text": "AyBendito: tell me",
        "annotation": []
    },
    {
        "text": "ImAnAnt: fr?",
        "annotation": []
    },
    {
        "text": "ImAnAnt: xD",
        "annotation": []
    },
    {
        "text": "CuckKania: this game is a fascusking joke ",
        "annotation": []
    },
    {
        "text": "AyBendito: what the fuck",
        "annotation": []
    },
    {
        "text": "CuckKania: 1 is lib",
        "annotation": []
    },
    {
        "text": "CuckKania: 6 is lib",
        "annotation": []
    },
    {
        "text": "AyBendito: did I do",
        "annotation": []
    },
    {
        "text": "QuinnWuest: idk i guess i cant make selfish picks in these lobbies",
        "annotation": []
    },
    {
        "text": "QuinnWuest: XD",
        "annotation": []
    },
    {
        "text": "CuckKania: 7 is likely lib ",
        "annotation": []
    },
    {
        "text": "RichRobby: HURRY THE FUCK UP AND MOVE ",
        "annotation": []
    },
    {
        "text": "AyBendito: wrong",
        "annotation": []
    },
    {
        "text": "AyBendito: nada",
        "annotation": []
    },
    {
        "text": "ImAnAnt: 2 passing is the dumbest shit I ever seen bruh",
        "annotation": []
    },
    {
        "text": "CuckKania: 3 can be lib tho",
        "annotation": []
    },
    {
        "text": "AyBendito: so stfu",
        "annotation": []
    },
    {
        "text": "SingSing: it's not even a selfish pick",
        "annotation": []
    },
    {
        "text": "SingSing: it's just a wrong pick",
        "annotation": []
    },
    {
        "text": "RichRobby: 5 stfu",
        "annotation": []
    },
    {
        "text": "CuckKania: but 2 is a fascist",
        "annotation": []
    },
    {
        "text": "RichRobby: if 2 is fascist ur tding to 3",
        "annotation": [
            "Consistency"
        ]
    },
    {
        "text": "AyBendito: 2 called 37 libs 6",
        "annotation": []
    },
    {
        "text": "QuinnWuest: ok 2",
        "annotation": []
    },
    {
        "text": "QuinnWuest: whats my pick then",
        "annotation": []
    },
    {
        "text": "AyBendito: why is 2 lib?",
        "annotation": []
    },
    {
        "text": "QuinnWuest: and dont say \"2\"",
        "annotation": []
    },
    {
        "text": "AyBendito: 6",
        "annotation": []
    },
    {
        "text": "SingSing: i didnt call 37 libs",
        "annotation": []
    },
    {
        "text": "RichRobby: call 234 when you guys neined 61 and wanted 73",
        "annotation": [
            "Consistency"
        ]
    },
    {
        "text": "ImAnAnt: why haven't we played 36 yet",
        "annotation": []
    },
    {
        "text": "CuckKania: if 2 is a fascist im jaing 16 XDD",
        "annotation": []
    },
    {
        "text": "SingSing: 1 also has no reading comprehension",
        "annotation": []
    },
    {
        "text": "ImAnAnt: 6 outed cnh refusing 16",
        "annotation": []
    },
    {
        "text": "AyBendito: talk to me",
        "annotation": []
    },
    {
        "text": "SingSing: which is why im never seing 1",
        "annotation": []
    },
    {
        "text": "AyBendito: why is 2 lib?",
        "annotation": []
    },
    {
        "text": "AyBendito: 2 asked for 73 ",
        "annotation": []
    },
    {
        "text": "SingSing: i said to 7,i dont think he should pick 3, because i dont htink 37 lib lib has 56 jaing like that",
        "annotation": []
    },
    {
        "text": "ImAnAnt: 2 legit tried to se 3 and 3 did not get se",
        "annotation": []
    },
    {
        "text": "QuinnWuest: 2 did the opposite",
        "annotation": []
    },
    {
        "text": "ImAnAnt: it's 157 or 257",
        "annotation": []
    },
    {
        "text": "QuinnWuest: lol",
        "annotation": []
    },
    {
        "text": "SingSing: and 1 keeps on misquoting me",
        "annotation": []
    },
    {
        "text": "ImAnAnt: the difference  does not matter",
        "annotation": []
    },
    {
        "text": "QuinnWuest: 2 asked for anything but 73",
        "annotation": []
    },
    {
        "text": "CuckKania: pick 6 again",
        "annotation": []
    },
    {
        "text": "AyBendito: 2 said 37 is lib lib ",
        "annotation": []
    },
    {
        "text": "QuinnWuest: literally",
        "annotation": []
    },
    {
        "text": "SingSing: no i didnt",
        "annotation": []
    },
    {
        "text": "QuinnWuest: not what happened at all",
        "annotation": []
    },
    {
        "text": "Inflated: bruh if 37 both lib 2 i am not wasting time or energy",
        "annotation": []
    },
    {
        "text": "CuckKania: if 16 doesnt pass idc anymore",
        "annotation": []
    },
    {
        "text": "AyBendito: Jad",
        "annotation": []
    },
    {
        "text": "Inflated: can we move",
        "annotation": []
    },
    {
        "text": "ImAnAnt: 3 didn't even lib 2 though",
        "annotation": [
            "Consistency"
        ]
    },
    {
        "text": "Inflated: 3 is punishing ",
        "annotation": []
    },
    {
        "text": "AyBendito: 15x",
        "annotation": []
    },
    {
        "text": "ImAnAnt: oh my goodness gracious",
        "annotation": []
    },
    {
        "text": "RichRobby: im punishing 1",
        "annotation": []
    },
    {
        "text": "Inflated: 1",
        "annotation": []
    },
    {
        "text": "AyBendito: sure",
        "annotation": []
    },
    {
        "text": "QuinnWuest: 1 just lying about what 2's chat was",
        "annotation": []
    },
    {
        "text": "QuinnWuest: so",
        "annotation": []
    },
    {
        "text": "Inflated: so 2 is lib",
        "annotation": []
    },
    {
        "text": "AyBendito: Stdu",
        "annotation": []
    },
    {
        "text": "AyBendito: stfu",
        "annotation": []
    },
    {
        "text": "RichRobby: 1 enjoy losing this gmae",
        "annotation": []
    },
    {
        "text": "SingSing: do i get SEd now after 1 misquotes me",
        "annotation": []
    },
    {
        "text": "SingSing: or im passing to 3",
        "annotation": []
    },
    {
        "text": "AyBendito: Stfu",
        "annotation": []
    },
    {
        "text": "ImAnAnt: 3 punishing 1 is a monstrosity",
        "annotation": []
    },
    {
        "text": "QuinnWuest: im jaing you 2",
        "annotation": []
    },
    {
        "text": "QuinnWuest: idk if 1/6 are",
        "annotation": []
    },
    {
        "text": "ImAnAnt: it's 3s game",
        "annotation": []
    },
    {
        "text": "RichRobby: do whatever u want 2 ",
        "annotation": []
    },
    {
        "text": "SingSing: well ofc u are",
        "annotation": []
    },
    {
        "text": "ImAnAnt: 1/2 has the last fascist",
        "annotation": []
    },
    {
        "text": "RichRobby: 1 deserves to be punished",
        "annotation": []
    },
    {
        "text": "RichRobby: for his transgressions",
        "annotation": []
    },
    {
        "text": "ImAnAnt: it legit does not matter",
        "annotation": []
    },
    {
        "text": "ImAnAnt: bro who cares",
        "annotation": []
    },
    {
        "text": "RichRobby: selfish fucker",
        "annotation": []
    },
    {
        "text": "ImAnAnt: 2 spent whole se libbing u",
        "annotation": []
    },
    {
        "text": "AyBendito: Actually ",
        "annotation": []
    },
    {
        "text": "CuckKania: 2 DIDNT",
        "annotation": []
    },
    {
        "text": "CuckKania: FUCKING",
        "annotation": []
    },
    {
        "text": "ImAnAnt: and no fascist stepped up to se 3 with 2",
        "annotation": []
    },
    {
        "text": "CuckKania: SE ",
        "annotation": []
    },
    {
        "text": "CuckKania: ANYBODY",
        "annotation": []
    },
    {
        "text": "CuckKania: 2 WAS STAYING FUCKING SILENT",
        "annotation": []
    },
    {
        "text": "AyBendito: I\u2019ll just ja 3 ",
        "annotation": []
    },
    {
        "text": "ImAnAnt: if 2 is liberal so is 3",
        "annotation": []
    },
    {
        "text": "RichRobby: and yet 1 stays",
        "annotation": []
    },
    {
        "text": "CuckKania: AND PAMING SE M,E",
        "annotation": []
    },
    {
        "text": "AyBendito: 73 played ",
        "annotation": []
    },
    {
        "text": "RichRobby: OH NOW 1 WANTS TO JA 3",
        "annotation": []
    },
    {
        "text": "QuinnWuest: bro",
        "annotation": []
    },
    {
        "text": "QuinnWuest: XD",
        "annotation": []
    },
    {
        "text": "RichRobby: NOW HE BRINGS UP THE 73",
        "annotation": []
    },
    {
        "text": "CuckKania: 6 ASKED 2 TO MAKE SE",
        "annotation": []
    },
    {
        "text": "RichRobby: NOW HE DOES",
        "annotation": []
    },
    {
        "text": "RichRobby: WOW",
        "annotation": []
    },
    {
        "text": "CuckKania: IN 16",
        "annotation": []
    },
    {
        "text": "AyBendito: I\u2019ll resign to 3",
        "annotation": []
    },
    {
        "text": "QuinnWuest: ok maybe it is 134",
        "annotation": []
    },
    {
        "text": "QuinnWuest: whatever",
        "annotation": []
    },
    {
        "text": "RichRobby: WAITS 10 MINUTES",
        "annotation": []
    },
    {
        "text": "AyBendito: fuck it",
        "annotation": []
    },
    {
        "text": "CuckKania: AND 2 DIDNT SAY A WORD ",
        "annotation": []
    },
    {
        "text": "ImAnAnt: im dead bruh",
        "annotation": []
    },
    {
        "text": "RichRobby: 7 fucking called 134 346 345",
        "annotation": []
    },
    {
        "text": "CuckKania: 4 is lying pick x5",
        "annotation": []
    },
    {
        "text": "AyBendito: ill punish libs if 3 is fas",
        "annotation": []
    },
    {
        "text": "RichRobby: 1 ur still being punisheed",
        "annotation": []
    },
    {
        "text": "ImAnAnt: yes 7 has called every single 34x line",
        "annotation": [
            "Authority"
        ]
    },
    {
        "text": "RichRobby: u dont get to be involved this game",
        "annotation": []
    },
    {
        "text": "QuinnWuest: 1 you are either misreading or lying about 2's chat",
        "annotation": []
    },
    {
        "text": "AyBendito: Idgaf",
        "annotation": []
    },
    {
        "text": "QuinnWuest: so you dont pass",
        "annotation": []
    },
    {
        "text": "QuinnWuest: simple as that",
        "annotation": []
    },
    {
        "text": "QuinnWuest: 2 argued for 7 n ot picking 3",
        "annotation": []
    },
    {
        "text": "SingSing: 6",
        "annotation": []
    },
    {
        "text": "SingSing: thoughts?",
        "annotation": []
    },
    {
        "text": "QuinnWuest: and is even trying to fas 7 for picking 3",
        "annotation": []
    },
    {
        "text": "ImAnAnt: xD",
        "annotation": []
    },
    {
        "text": "QuinnWuest: and youre saying he wanted 73",
        "annotation": []
    },
    {
        "text": "Inflated: i denied my chancellor",
        "annotation": []
    },
    {
        "text": "QuinnWuest: ur just misreading or lying",
        "annotation": []
    },
    {
        "text": "AyBendito: ill give you the game 3 ",
        "annotation": []
    },
    {
        "text": "Inflated: twice",
        "annotation": []
    },
    {
        "text": "QuinnWuest: so you dont pass",
        "annotation": []
    },
    {
        "text": "Inflated: and you ask me",
        "annotation": []
    },
    {
        "text": "SingSing: yes",
        "annotation": []
    },
    {
        "text": "SingSing: so like",
        "annotation": []
    },
    {
        "text": "QuinnWuest: idk 2",
        "annotation": []
    },
    {
        "text": "SingSing: u want 3 to play?",
        "annotation": []
    },
    {
        "text": "QuinnWuest: just pick either of 56",
        "annotation": []
    },
    {
        "text": "QuinnWuest: idc which",
        "annotation": []
    },
    {
        "text": "Inflated: i mean im lazy",
        "annotation": []
    },
    {
        "text": "Inflated: idc",
        "annotation": []
    },
    {
        "text": "QuinnWuest: i prefer 6",
        "annotation": []
    },
    {
        "text": "SingSing: ok ill lazy ja",
        "annotation": []
    },
    {
        "text": "ImAnAnt: 1 has libbed 3 bro",
        "annotation": []
    },
    {
        "text": "Inflated: i ll ja 2 or 3",
        "annotation": []
    },
    {
        "text": "ImAnAnt: im dead bruh",
        "annotation": []
    },
    {
        "text": "AyBendito: I give 3 the game 7 picked 3 ",
        "annotation": []
    },
    {
        "text": "SingSing: i mean im lazy jaing if this gets neined then 3 plays np",
        "annotation": []
    },
    {
        "text": "SingSing: im never denying my own gov",
        "annotation": []
    },
    {
        "text": "RichRobby: well im not going to give 5 any lib equity this game",
        "annotation": []
    },
    {
        "text": "RichRobby: going to be open about that",
        "annotation": []
    },
    {
        "text": "AyBendito: 3 fasses me for shit",
        "annotation": []
    },
    {
        "text": "SingSing: when 6 neins himself as chance",
        "annotation": []
    },
    {
        "text": "RichRobby: wym for shit",
        "annotation": []
    },
    {
        "text": "AyBendito: fuck you ",
        "annotation": []
    },
    {
        "text": "CuckKania: wdym  you will ja 2 or 3",
        "annotation": []
    },
    {
        "text": "SingSing: if he's hitler he can win rofl",
        "annotation": []
    },
    {
        "text": "RichRobby: 7 picked 73 over picking urself or 6",
        "annotation": []
    },
    {
        "text": "AyBendito: stfu",
        "annotation": []
    },
    {
        "text": "RichRobby: and u dont undersadn how 7 is resigned fascist",
        "annotation": []
    },
    {
        "text": "QuinnWuest: @1 if all of 2347 are fasing you,",
        "annotation": []
    },
    {
        "text": "AyBendito: please ",
        "annotation": []
    },
    {
        "text": "RichRobby: and 3 is resigned lib",
        "annotation": []
    },
    {
        "text": "ImAnAnt: is 5 hitler or what",
        "annotation": []
    },
    {
        "text": "QuinnWuest: maybe you did somethign wrong",
        "annotation": []
    },
    {
        "text": "QuinnWuest: !!",
        "annotation": []
    },
    {
        "text": "ImAnAnt: vote",
        "annotation": []
    },
    {
        "text": "RichRobby: u get to lose ",
        "annotation": []
    },
    {
        "text": "CuckKania: 1 is asking for 36",
        "annotation": []
    },
    {
        "text": "CuckKania: 6 is jaing either 2 or 3",
        "annotation": []
    },
    {
        "text": "AyBendito: 3 stfu",
        "annotation": []
    },
    {
        "text": "AyBendito: ty",
        "annotation": []
    },
    {
        "text": "CuckKania: you have to state",
        "annotation": []
    },
    {
        "text": "SingSing: iit's not 345 either",
        "annotation": []
    },
    {
        "text": "CuckKania: what yorue  xoing ",
        "annotation": []
    },
    {
        "text": "CuckKania: xd",
        "annotation": []
    },
    {
        "text": "AyBendito: Idc anymore",
        "annotation": []
    },
    {
        "text": "Inflated: ok just ja 3",
        "annotation": []
    },
    {
        "text": "Inflated: sigh",
        "annotation": []
    },
    {
        "text": "SingSing: vote whatever u want",
        "annotation": []
    },
    {
        "text": "QuinnWuest: ok",
        "annotation": []
    },
    {
        "text": "SingSing: ye",
        "annotation": []
    },
    {
        "text": "QuinnWuest: XDDDDDDDDDDDDDDDDDDDDDDDDD",
        "annotation": []
    },
    {
        "text": "QuinnWuest: yall are so ass",
        "annotation": []
    },
    {
        "text": "QuinnWuest: esp 1",
        "annotation": []
    },
    {
        "text": "Inflated: holy fuck",
        "annotation": []
    },
    {
        "text": "AyBendito: i really don\u2019t care ",
        "annotation": []
    },
    {
        "text": "QuinnWuest: btw",
        "annotation": []
    },
    {
        "text": "SingSing: td blue?",
        "annotation": []
    },
    {
        "text": "QuinnWuest: right",
        "annotation": []
    },
    {
        "text": "Inflated: im tired",
        "annotation": []
    },
    {
        "text": "AyBendito: Nah",
        "annotation": []
    },
    {
        "text": "RichRobby: AREOYF",
        "annotation": []
    },
    {
        "text": "ImAnAnt: BRO",
        "annotation": []
    },
    {
        "text": "RichRobby: 'DAS",
        "annotation": []
    },
    {
        "text": "CuckKania: YES TD WR",
        "annotation": []
    },
    {
        "text": "CuckKania: TD WR HARD CARRY",
        "annotation": []
    },
    {
        "text": "RichRobby: AYBENDITO IS FUCKING FASCIST TOO",
        "annotation": []
    },
    {
        "text": "RichRobby: U CANT BE SERIOUS",
        "annotation": []
    },
    {
        "text": "CuckKania: TD WR",
        "annotation": []
    },
    {
        "text": "RichRobby: HELL NO",
        "annotation": []
    }
]