[
    {
        "text": "Gamethrower: so 7 doesn't wish to play",
        "annotation": []
    },
    {
        "text": "Gamethrower: noted",
        "annotation": []
    },
    {
        "text": "Gamethrower: 7 can have his wish",
        "annotation": []
    },
    {
        "text": "MommyOrDaddy: Sus 7",
        "annotation": []
    },
    {
        "text": "Gamethrower: he is skipped every pre hz gov",
        "annotation": []
    },
    {
        "text": "MommyOrDaddy: 7 has info as lib ",
        "annotation": []
    },
    {
        "text": "MommyOrDaddy: very sus",
        "annotation": []
    },
    {
        "text": "sillylogic: 346 nein",
        "annotation": []
    },
    {
        "text": "Gamesolver: 257 pro triangle",
        "annotation": []
    },
    {
        "text": "Gamesolver: :thumbsup:",
        "annotation": []
    },
    {
        "text": "Gamethrower: 5 jad 14 so I like 5 ",
        "annotation": []
    },
    {
        "text": "Gamethrower: and idea of 51 after",
        "annotation": []
    },
    {
        "text": "Gamesolver: kek",
        "annotation": []
    },
    {
        "text": "Gamesolver: 4, what was that? I have info as lib",
        "annotation": []
    },
    {
        "text": "Gamesolver: or what did u just say",
        "annotation": []
    },
    {
        "text": "Gamesolver: lmao",
        "annotation": []
    },
    {
        "text": "Gamethrower: u neind 14",
        "annotation": []
    },
    {
        "text": "Gamethrower: that's extremely suspcious behavior",
        "annotation": []
    },
    {
        "text": "Gamesolver: well yes ",
        "annotation": []
    },
    {
        "text": "omichManiac: who jad me",
        "annotation": []
    },
    {
        "text": "omichManiac: btw",
        "annotation": []
    },
    {
        "text": "FacismSux: 23456",
        "annotation": []
    },
    {
        "text": "Gamesolver: I always nein 14 as 7",
        "annotation": []
    },
    {
        "text": "Gamesolver: kek",
        "annotation": []
    },
    {
        "text": "Gamesolver: pretty much always ",
        "annotation": []
    },
    {
        "text": "MommyOrDaddy: okay 1",
        "annotation": []
    },
    {
        "text": "Gamethrower: 51",
        "annotation": []
    },
    {
        "text": "Gamethrower: or 52 okay.",
        "annotation": []
    },
    {
        "text": "Gamethrower: thought I could get 52",
        "annotation": []
    },
    {
        "text": "Gamesolver: whatever i press ja",
        "annotation": []
    },
    {
        "text": "Gamethrower: *51",
        "annotation": []
    },
    {
        "text": "Gamethrower: good try by me",
        "annotation": []
    },
    {
        "text": "Gamesolver: 3 is confirmed fac tho",
        "annotation": []
    },
    {
        "text": "Gamesolver: so ez game",
        "annotation": []
    },
    {
        "text": "omichManiac: shut up",
        "annotation": []
    },
    {
        "text": "Gamesolver: RRR and jas 41 lol",
        "annotation": []
    },
    {
        "text": "Gamethrower: inv 2 ",
        "annotation": []
    },
    {
        "text": "Gamethrower: u tl'd him",
        "annotation": []
    },
    {
        "text": "sillylogic: inv me",
        "annotation": []
    },
    {
        "text": "Gamethrower: click ur chancellor",
        "annotation": []
    },
    {
        "text": "Gamethrower: not very believable but ok.",
        "annotation": []
    },
    {
        "text": "MommyOrDaddy: I feel like everyone outed fas ",
        "annotation": []
    },
    {
        "text": "omichManiac: well",
        "annotation": []
    },
    {
        "text": "omichManiac: this is awkward",
        "annotation": []
    },
    {
        "text": "omichManiac: 36 is rrb",
        "annotation": []
    },
    {
        "text": "Gamethrower: your fault 3",
        "annotation": []
    },
    {
        "text": "MommyOrDaddy: Ok se 4",
        "annotation": []
    },
    {
        "text": "Gamethrower: for being a monkey",
        "annotation": []
    },
    {
        "text": "sillylogic: wow",
        "annotation": []
    },
    {
        "text": "omichManiac: i didnt expect you all to ja 6",
        "annotation": []
    },
    {
        "text": "Gamethrower: I mean 3's lib too",
        "annotation": []
    },
    {
        "text": "Gamethrower: why would we not?",
        "annotation": []
    },
    {
        "text": "Gamethrower: 61 is perfectly reasonable gov",
        "annotation": []
    },
    {
        "text": "omichManiac: like monkeys",
        "annotation": []
    },
    {
        "text": "Stalin13: SE 2 I guess",
        "annotation": []
    },
    {
        "text": "Gamethrower: no you're the monkey lol",
        "annotation": []
    },
    {
        "text": "MommyOrDaddy: Why did 61 pass",
        "annotation": []
    },
    {
        "text": "sillylogic: I would like to be in se convo",
        "annotation": []
    },
    {
        "text": "FacismSux: got 4 jas",
        "annotation": []
    },
    {
        "text": "omichManiac: 1256 jad",
        "annotation": []
    },
    {
        "text": "Gamethrower: well 3 is liberal",
        "annotation": []
    },
    {
        "text": "Gamesolver: eh",
        "annotation": []
    },
    {
        "text": "Gamesolver: well",
        "annotation": []
    },
    {
        "text": "omichManiac: 36 is rrb conf",
        "annotation": []
    },
    {
        "text": "Gamethrower: 6 just dd'd 13",
        "annotation": []
    },
    {
        "text": "Gamethrower: but 3 is the worst lib I've ever played with",
        "annotation": []
    },
    {
        "text": "Gamesolver: im gonna do something exploitative i guess",
        "annotation": []
    },
    {
        "text": "Gamesolver: and i'll nein any SE to 1",
        "annotation": []
    },
    {
        "text": "Stalin13: How is 3 liveral as red prez",
        "annotation": []
    },
    {
        "text": "Gamesolver: pretty sure 1 is lib!",
        "annotation": []
    },
    {
        "text": "Gamethrower: ok",
        "annotation": []
    },
    {
        "text": "Gamethrower: huge!",
        "annotation": []
    },
    {
        "text": "Gamesolver: more than any other player",
        "annotation": []
    },
    {
        "text": "sillylogic: @5, 3 6 conflict",
        "annotation": []
    },
    {
        "text": "MommyOrDaddy: Ok we aren't seing in conf ",
        "annotation": []
    },
    {
        "text": "Gamethrower: well that's pretty liberal from 7 ",
        "annotation": []
    },
    {
        "text": "Gamethrower: lol",
        "annotation": []
    },
    {
        "text": "FacismSux: 245 are three libs we chill then",
        "annotation": []
    },
    {
        "text": "Gamethrower: well 4",
        "annotation": []
    },
    {
        "text": "Gamesolver: Well is it really a conflict lol",
        "annotation": []
    },
    {
        "text": "Gamesolver: i think",
        "annotation": []
    },
    {
        "text": "FacismSux: se eachother",
        "annotation": []
    },
    {
        "text": "Gamethrower: do u think line is 137",
        "annotation": []
    },
    {
        "text": "Gamesolver: 2/5 both have no reason to ja this gov",
        "annotation": []
    },
    {
        "text": "omichManiac: ill nein to 1 aswell",
        "annotation": []
    },
    {
        "text": "Gamethrower: basically my only fas line right",
        "annotation": []
    },
    {
        "text": "Gamesolver: so the SE should always be in 4/7 regardless",
        "annotation": []
    },
    {
        "text": "Gamesolver: but i like 1",
        "annotation": []
    },
    {
        "text": "MommyOrDaddy: I mean could be why is 7 seing u",
        "annotation": []
    },
    {
        "text": "MommyOrDaddy: when he neined 14",
        "annotation": []
    },
    {
        "text": "Stalin13: @2, there is 16 conflict, 3 was red prez",
        "annotation": []
    },
    {
        "text": "Gamethrower: b/c he thinks I'm clear lib",
        "annotation": [
            "Friendship/Liking"
        ]
    },
    {
        "text": "Gamesolver: 17 both have played extremely liberal to 5s pov",
        "annotation": [
            "Consistency"
        ]
    },
    {
        "text": "MommyOrDaddy: and jas 61",
        "annotation": []
    },
    {
        "text": "Gamesolver: and he shits on us both",
        "annotation": []
    },
    {
        "text": "Gamesolver: the entire game",
        "annotation": []
    },
    {
        "text": "omichManiac: 5, 36 was rrb aswell",
        "annotation": []
    },
    {
        "text": "sillylogic: 3 reclaimed rrb, see chat 5",
        "annotation": []
    },
    {
        "text": "Gamethrower: well 5 is definitely fascist lol",
        "annotation": []
    },
    {
        "text": "Gamethrower: that much is clear",
        "annotation": []
    },
    {
        "text": "sillylogic: 1 minute left",
        "annotation": []
    },
    {
        "text": "Gamethrower: it's 56x",
        "annotation": []
    },
    {
        "text": "MommyOrDaddy: I'm the only one who played liberal and voted correctly ",
        "annotation": [
            "Authority"
        ]
    },
    {
        "text": "Gamethrower: dunno x yet",
        "annotation": []
    },
    {
        "text": "Gamesolver: well ya agreed that it's 56x",
        "annotation": [
            "Consistency"
        ]
    },
    {
        "text": "Gamethrower: how did I not vote liberally",
        "annotation": []
    },
    {
        "text": "Gamethrower: to 4",
        "annotation": []
    },
    {
        "text": "Stalin13: Wow, quite a leap 7",
        "annotation": []
    },
    {
        "text": "MommyOrDaddy: Because u jad 6",
        "annotation": []
    },
    {
        "text": "Gamethrower: also 17x and I kinda chatconfd 7",
        "annotation": []
    },
    {
        "text": "Gamesolver: Not quite a leap 5",
        "annotation": []
    },
    {
        "text": "Gamesolver: you voted like a fascist",
        "annotation": []
    },
    {
        "text": "Gamethrower: how am I supposed to not ja 61",
        "annotation": []
    },
    {
        "text": "Gamesolver: i respect it but youre fac",
        "annotation": []
    },
    {
        "text": "Gamethrower: it's unljely to be 256",
        "annotation": []
    },
    {
        "text": "Gamethrower: if 3 rrr is real",
        "annotation": []
    },
    {
        "text": "Gamethrower: lol",
        "annotation": []
    },
    {
        "text": "sillylogic: also, only 3b so far even with 3 reclaiming rrb",
        "annotation": []
    },
    {
        "text": "omichManiac: now its very likely",
        "annotation": []
    },
    {
        "text": "Gamethrower: how am I to know 36 is rrb",
        "annotation": []
    },
    {
        "text": "FacismSux: ill click 4 on timer since 2 can still be neined too",
        "annotation": []
    },
    {
        "text": "omichManiac: is it not",
        "annotation": []
    },
    {
        "text": "Gamesolver: 2 can not still be neined to",
        "annotation": []
    },
    {
        "text": "Gamesolver: lol",
        "annotation": []
    },
    {
        "text": "Gamethrower: ye it's quite likely now",
        "annotation": []
    },
    {
        "text": "Gamethrower: well 6 is giga outed",
        "annotation": []
    },
    {
        "text": "Gamethrower: who cares rly",
        "annotation": []
    },
    {
        "text": "Gamesolver: 6 is confirmed fascist now",
        "annotation": []
    },
    {
        "text": "Gamesolver: with his SE logic",
        "annotation": []
    },
    {
        "text": "Gamethrower: also 5 is like basically outed by deck",
        "annotation": []
    },
    {
        "text": "Gamethrower: lol",
        "annotation": []
    },
    {
        "text": "Stalin13: So currently we have 16 conflict, 36 conflict and me as red prez",
        "annotation": []
    },
    {
        "text": "Gamethrower: cuz he inv'd the only other toucher (2) as lib",
        "annotation": []
    },
    {
        "text": "FacismSux: we can nein to 2, id rathe rnot td to 4 tho",
        "annotation": []
    },
    {
        "text": "MommyOrDaddy: 23 are u here",
        "annotation": []
    },
    {
        "text": "FacismSux: so se 4 is logical",
        "annotation": []
    },
    {
        "text": "Gamethrower: well 3 alr said he'd ja me",
        "annotation": [
            "Reciprocation"
        ]
    },
    {
        "text": "Gamethrower: as he should",
        "annotation": [
            "Reciprocation"
        ]
    },
    {
        "text": "sillylogic: yeah, I am happy to call 56x as well",
        "annotation": []
    },
    {
        "text": "Gamethrower: 16x is silly",
        "annotation": []
    },
    {
        "text": "Gamesolver: no we cant nein to 2",
        "annotation": []
    },
    {
        "text": "Gamesolver: without it being TD",
        "annotation": []
    },
    {
        "text": "Gamethrower: ok well 2 calls me lib lol",
        "annotation": []
    },
    {
        "text": "omichManiac: 2 calls 56x",
        "annotation": []
    },
    {
        "text": "Gamethrower: he said 56x",
        "annotation": []
    },
    {
        "text": "FacismSux: bro check track",
        "annotation": []
    },
    {
        "text": "omichManiac: we nein to 1 then",
        "annotation": []
    },
    {
        "text": "Gamethrower: so I get neined to?",
        "annotation": []
    },
    {
        "text": "Gamesolver: ya",
        "annotation": []
    },
    {
        "text": "FacismSux: oh wait",
        "annotation": []
    },
    {
        "text": "Gamesolver: lets nein to 1",
        "annotation": []
    },
    {
        "text": "sillylogic: yeah, 6 outs ",
        "annotation": []
    },
    {
        "text": "Gamethrower: ok",
        "annotation": []
    },
    {
        "text": "MommyOrDaddy: Why are we jaing a conf ",
        "annotation": []
    },
    {
        "text": "Gamethrower: well 2 might be lib then",
        "annotation": []
    },
    {
        "text": "Gamethrower: haha",
        "annotation": []
    },
    {
        "text": "Gamethrower: 4 ur fas right in 456",
        "annotation": []
    },
    {
        "text": "MommyOrDaddy: when we can se a lib",
        "annotation": []
    },
    {
        "text": "Gamethrower: xD",
        "annotation": []
    },
    {
        "text": "Stalin13: 2 is lib",
        "annotation": []
    },
    {
        "text": "MommyOrDaddy: No I'm not 1",
        "annotation": []
    },
    {
        "text": "Gamethrower: ok then why are you not honoring 2",
        "annotation": [
            "Consistency"
        ]
    },
    {
        "text": "Gamethrower: saying I'm lib",
        "annotation": []
    },
    {
        "text": "MommyOrDaddy: they see ur pink ",
        "annotation": []
    },
    {
        "text": "MommyOrDaddy: and wanna se u",
        "annotation": []
    },
    {
        "text": "Gamethrower: not true at all",
        "annotation": []
    },
    {
        "text": "omichManiac: lol",
        "annotation": []
    },
    {
        "text": "Gamethrower: 2 didn't try to SE me",
        "annotation": []
    },
    {
        "text": "Gamethrower: he just said 6 is outed",
        "annotation": []
    },
    {
        "text": "MommyOrDaddy: It's pure racism ",
        "annotation": []
    },
    {
        "text": "Gamethrower: for his SE actions",
        "annotation": []
    },
    {
        "text": "Gamethrower: which is accurate",
        "annotation": []
    },
    {
        "text": "Gamesolver: well 156 is possible which would be funny",
        "annotation": []
    },
    {
        "text": "Gamesolver: hehe",
        "annotation": []
    },
    {
        "text": "omichManiac: kudos to 6",
        "annotation": []
    },
    {
        "text": "omichManiac: if its 156",
        "annotation": []
    },
    {
        "text": "Stalin13: 7, you aren't adding any value",
        "annotation": []
    },
    {
        "text": "Gamethrower: if it's 16x 6 carried me hard",
        "annotation": [
            "Reciprocation"
        ]
    },
    {
        "text": "Gamethrower: XD",
        "annotation": []
    },
    {
        "text": "MommyOrDaddy: I wanna ja this",
        "annotation": []
    },
    {
        "text": "omichManiac: well i prefer 1x",
        "annotation": []
    },
    {
        "text": "Gamethrower: 3 is openly neining to me",
        "annotation": []
    },
    {
        "text": "Gamethrower: and 5 outs",
        "annotation": []
    },
    {
        "text": "Gamethrower: jaing 43",
        "annotation": []
    },
    {
        "text": "omichManiac: hey 7",
        "annotation": []
    },
    {
        "text": "Gamethrower: so 5 is resigned",
        "annotation": []
    },
    {
        "text": "omichManiac: 6 is totally ok with neining to 1",
        "annotation": []
    },
    {
        "text": "omichManiac: im worried",
        "annotation": []
    },
    {
        "text": "Gamesolver: ok",
        "annotation": []
    },
    {
        "text": "Gamethrower: bro cmon ",
        "annotation": []
    },
    {
        "text": "Gamesolver: well",
        "annotation": []
    },
    {
        "text": "Gamethrower: 5 just outed fas",
        "annotation": []
    },
    {
        "text": "Gamesolver: 56x is outed now",
        "annotation": []
    },
    {
        "text": "Gamethrower: to ja 43",
        "annotation": []
    },
    {
        "text": "Gamethrower: lol",
        "annotation": []
    },
    {
        "text": "Gamesolver: so if u wanna ja me that's cool",
        "annotation": []
    },
    {
        "text": "Stalin13: I'd rather not have 1x with 1 in conflict",
        "annotation": []
    },
    {
        "text": "Gamesolver: i wanna play a gov and blast 5",
        "annotation": []
    },
    {
        "text": "FacismSux: agreed 5",
        "annotation": []
    },
    {
        "text": "Gamesolver: or uh",
        "annotation": []
    },
    {
        "text": "Gamesolver: 6 i guess",
        "annotation": []
    },
    {
        "text": "Gamesolver: lol",
        "annotation": []
    },
    {
        "text": "sillylogic: I am happy to ja 1x",
        "annotation": []
    },
    {
        "text": "Gamethrower: ok well",
        "annotation": []
    },
    {
        "text": "Gamethrower: 2 still calls me lib",
        "annotation": []
    },
    {
        "text": "Gamethrower: can't be 12x",
        "annotation": []
    },
    {
        "text": "Gamesolver: well whatever lets go 1x then",
        "annotation": []
    },
    {
        "text": "Gamesolver: kek",
        "annotation": []
    },
    {
        "text": "MommyOrDaddy: We can nein to 1",
        "annotation": []
    },
    {
        "text": "Gamethrower: so I should still pvss",
        "annotation": []
    },
    {
        "text": "omichManiac: ok sure",
        "annotation": []
    },
    {
        "text": "omichManiac: 1x it is",
        "annotation": []
    },
    {
        "text": "Gamethrower: should I take gun lol",
        "annotation": []
    },
    {
        "text": "omichManiac: ye probs",
        "annotation": []
    },
    {
        "text": "omichManiac: its funnier",
        "annotation": []
    },
    {
        "text": "MommyOrDaddy: I'll say 567 ",
        "annotation": []
    },
    {
        "text": "Gamethrower: I'll click omich",
        "annotation": []
    },
    {
        "text": "Gamethrower: if he's hitler wp 6",
        "annotation": []
    },
    {
        "text": "Stalin13: Dafuq",
        "annotation": []
    },
    {
        "text": "Gamethrower: well",
        "annotation": []
    },
    {
        "text": "Gamesolver: so uh",
        "annotation": []
    },
    {
        "text": "Gamethrower: which of 56 should I shoot",
        "annotation": []
    },
    {
        "text": "Gamesolver: whats going on",
        "annotation": []
    },
    {
        "text": "Gamethrower: they're both outed",
        "annotation": []
    },
    {
        "text": "Gamesolver: hehe",
        "annotation": []
    },
    {
        "text": "FacismSux: im still alive",
        "annotation": []
    },
    {
        "text": "Gamethrower: 3 gave gun I guess",
        "annotation": []
    },
    {
        "text": "omichManiac: 6 obv",
        "annotation": []
    },
    {
        "text": "FacismSux: XD",
        "annotation": []
    },
    {
        "text": "Gamesolver: shoot 6",
        "annotation": []
    },
    {
        "text": "omichManiac: i gave",
        "annotation": []
    },
    {
        "text": "omichManiac: ofc",
        "annotation": []
    },
    {
        "text": "Stalin13: Dafuq",
        "annotation": []
    },
    {
        "text": "MommyOrDaddy: 5 is hitler",
        "annotation": []
    },
    {
        "text": "MommyOrDaddy: i feel it",
        "annotation": []
    },
    {
        "text": "FacismSux: i have food to make can i go ",
        "annotation": []
    },
    {
        "text": "sillylogic: lol, i would shoot 5",
        "annotation": []
    },
    {
        "text": "Stalin13: 13 both super sus",
        "annotation": []
    },
    {
        "text": "Gamethrower: I don't need to shoot my conf",
        "annotation": []
    },
    {
        "text": "FacismSux: nooo",
        "annotation": []
    },
    {
        "text": "Gamesolver: well whatever",
        "annotation": []
    },
    {
        "text": "Gamethrower: 2 said to shoot 5",
        "annotation": []
    },
    {
        "text": "Gamethrower: so I do",
        "annotation": []
    },
    {
        "text": "Gamesolver: i ja 27",
        "annotation": []
    },
    {
        "text": "MommyOrDaddy: 1 didn't shoot his conf ",
        "annotation": []
    },
    {
        "text": "MommyOrDaddy: 16 ff in a world?",
        "annotation": []
    },
    {
        "text": "Gamethrower: ok 16x in what line",
        "annotation": []
    },
    {
        "text": "Gamethrower: 136?",
        "annotation": []
    },
    {
        "text": "Gamesolver: yeah it could be 136 or some shit",
        "annotation": []
    },
    {
        "text": "Gamethrower: lol",
        "annotation": []
    },
    {
        "text": "Gamesolver: u dont shoot ur conflict brooo",
        "annotation": []
    },
    {
        "text": "sillylogic: well, 5 was likely hitler",
        "annotation": []
    },
    {
        "text": "Gamesolver: lol",
        "annotation": []
    },
    {
        "text": "Gamethrower: well 2 i'll ja you on 24 or 27",
        "annotation": []
    },
    {
        "text": "Gamesolver: take gun to not shoot ur conflict ",
        "annotation": []
    },
    {
        "text": "Gamethrower: either one",
        "annotation": []
    },
    {
        "text": "sillylogic: but if not, then I guess the loss is on me",
        "annotation": []
    },
    {
        "text": "Gamethrower: 24/27 you can pvss",
        "annotation": []
    },
    {
        "text": "Gamesolver: lmao",
        "annotation": []
    },
    {
        "text": "Gamethrower: if you want 2",
        "annotation": []
    },
    {
        "text": "MommyOrDaddy: We lost ",
        "annotation": []
    },
    {
        "text": "omichManiac: probably",
        "annotation": []
    },
    {
        "text": "Gamethrower: I mean I thought 5's hitler",
        "annotation": []
    },
    {
        "text": "Gamethrower: 2 is prob hitler",
        "annotation": []
    },
    {
        "text": "Gamethrower: cuz he's supporting libs",
        "annotation": []
    },
    {
        "text": "Gamethrower: but I'll ja 24/27",
        "annotation": []
    },
    {
        "text": "Gamethrower: lol",
        "annotation": []
    },
    {
        "text": "sillylogic: lol, I am lib",
        "annotation": []
    },
    {
        "text": "Gamesolver: ok make a pick then 2",
        "annotation": []
    },
    {
        "text": "MommyOrDaddy: I mean u guys trolled seing in conf ",
        "annotation": []
    },
    {
        "text": "FacismSux: pick",
        "annotation": []
    },
    {
        "text": "Gamethrower: pick whoever is more cnh in 4/7",
        "annotation": []
    },
    {
        "text": "Gamethrower: ur passing",
        "annotation": []
    },
    {
        "text": "sillylogic: and I do not want to pick in 4/7 cause one of them is hitty then",
        "annotation": []
    },
    {
        "text": "Gamethrower: 6 could be still techically",
        "annotation": []
    },
    {
        "text": "omichManiac: correct",
        "annotation": []
    },
    {
        "text": "Gamesolver: I mean i SE'd 1 i dont see why i would do that",
        "annotation": []
    },
    {
        "text": "Gamesolver: in chaotic gamestate",
        "annotation": []
    },
    {
        "text": "sillylogic: well, I think 4 is more hitty than 7",
        "annotation": []
    },
    {
        "text": "MommyOrDaddy: ??",
        "annotation": []
    },
    {
        "text": "Gamesolver: pick me then 2?",
        "annotation": []
    },
    {
        "text": "MommyOrDaddy: how",
        "annotation": []
    },
    {
        "text": "FacismSux: pickpickpick",
        "annotation": []
    },
    {
        "text": "MommyOrDaddy: Im liberal ",
        "annotation": []
    },
    {
        "text": "MommyOrDaddy: I played like one ",
        "annotation": []
    },
    {
        "text": "sillylogic: ahh, this sucks",
        "annotation": []
    },
    {
        "text": "MommyOrDaddy: no",
        "annotation": []
    },
    {
        "text": "Gamethrower: 27 unless 4 prefers calling 2 cnh",
        "annotation": []
    },
    {
        "text": "Gamethrower: it's 27 or x2",
        "annotation": []
    },
    {
        "text": "Gamethrower: up to 4",
        "annotation": []
    },
    {
        "text": "MommyOrDaddy: tive me td odds honestly ",
        "annotation": []
    },
    {
        "text": "Gamesolver: no lol",
        "annotation": []
    },
    {
        "text": "Gamethrower: no I'm jaing this unless you take x2",
        "annotation": []
    },
    {
        "text": "Gamethrower: it's up to you 4",
        "annotation": []
    },
    {
        "text": "Gamethrower: ur not ff right so",
        "annotation": []
    },
    {
        "text": "Gamethrower: if you want 42 that's fine",
        "annotation": []
    },
    {
        "text": "Gamethrower: everyone in 1237 is confirmed lib if you out",
        "annotation": [
            "Social Validation"
        ]
    },
    {
        "text": "Gamethrower: lol",
        "annotation": []
    },
    {
        "text": "MommyOrDaddy: okay I'll take",
        "annotation": []
    },
    {
        "text": "Gamesolver: no",
        "annotation": []
    },
    {
        "text": "Gamesolver: just ja the gov lol",
        "annotation": []
    },
    {
        "text": "Gamethrower: well sure",
        "annotation": []
    },
    {
        "text": "Gamethrower: 42 can play",
        "annotation": []
    },
    {
        "text": "MommyOrDaddy: no I don't trust u ",
        "annotation": []
    },
    {
        "text": "Gamethrower: but if you go 47 ur outed",
        "annotation": [
            "Scarcity"
        ]
    },
    {
        "text": "Gamethrower: xd",
        "annotation": []
    },
    {
        "text": "Gamesolver: dude",
        "annotation": []
    },
    {
        "text": "Gamesolver: just press ja on the gov",
        "annotation": []
    },
    {
        "text": "Gamesolver: why do you give",
        "annotation": []
    },
    {
        "text": "Gamesolver: 4 the option",
        "annotation": []
    },
    {
        "text": "Gamethrower: I'm pretty sure 2's hitler too",
        "annotation": []
    },
    {
        "text": "Gamesolver: 24 both played like hitler 7 didnt",
        "annotation": []
    },
    {
        "text": "Gamesolver: so why dont you just ja the gov",
        "annotation": [
            "Consistency"
        ]
    },
    {
        "text": "Gamesolver: 125 is impossible",
        "annotation": []
    },
    {
        "text": "Gamesolver: ure essentially",
        "annotation": []
    },
    {
        "text": "Gamethrower: cuz 4 wants to call 2 cnh",
        "annotation": []
    },
    {
        "text": "Gamesolver: playing into the hands of the fascists",
        "annotation": []
    },
    {
        "text": "Gamethrower: so that's his right",
        "annotation": []
    },
    {
        "text": "Gamethrower: if he outs 1237 are all libs",
        "annotation": []
    },
    {
        "text": "Gamesolver: i mean its 146 then or some shit",
        "annotation": []
    },
    {
        "text": "Gamesolver: whatever",
        "annotation": []
    },
    {
        "text": "Gamesolver: just go",
        "annotation": []
    },
    {
        "text": "Gamethrower: if 4 picks outside 27 we also obv td",
        "annotation": []
    },
    {
        "text": "Gamesolver: i mean 4 is not lib",
        "annotation": []
    },
    {
        "text": "Gamesolver: kek",
        "annotation": []
    },
    {
        "text": "FacismSux: :cry: ",
        "annotation": []
    },
    {
        "text": "Gamethrower: if he outs 1237 are all libs",
        "annotation": []
    },
    {
        "text": "Gamethrower: so just play whatever",
        "annotation": []
    },
    {
        "text": "Gamethrower: lol",
        "annotation": []
    },
    {
        "text": "Gamethrower: shoot 6 if ur lib obv",
        "annotation": []
    },
    {
        "text": "Gamethrower: only legal shot brother",
        "annotation": [
            "Friendship/Liking"
        ]
    },
    {
        "text": "Gamesolver: gj not jaing 27 tom",
        "annotation": []
    },
    {
        "text": "Gamesolver: when u had power",
        "annotation": []
    },
    {
        "text": "Gamethrower: so what 7",
        "annotation": []
    },
    {
        "text": "Gamesolver: so what? we in vz ",
        "annotation": []
    },
    {
        "text": "Gamethrower: 1237 are all confirmed",
        "annotation": []
    },
    {
        "text": "Gamesolver: is win guaranteed",
        "annotation": []
    },
    {
        "text": "Gamethrower: we can't lose?",
        "annotation": []
    },
    {
        "text": "Gamesolver: lol",
        "annotation": []
    },
    {
        "text": "MommyOrDaddy: 1 we can't shoot 6 don't bm lol",
        "annotation": []
    },
    {
        "text": "Gamethrower: tbf we can lose ",
        "annotation": []
    },
    {
        "text": "omichManiac: we lose to what",
        "annotation": []
    },
    {
        "text": "omichManiac: 99%",
        "annotation": []
    },
    {
        "text": "omichManiac: if i count correctly",
        "annotation": []
    },
    {
        "text": "omichManiac: 1237 are all libs",
        "annotation": []
    },
    {
        "text": "Gamethrower: play the gov that you have to skip 2 people",
        "annotation": []
    },
    {
        "text": "Gamethrower: in this deck btw",
        "annotation": []
    },
    {
        "text": "Gamethrower: not new deck",
        "annotation": []
    },
    {
        "text": "Gamethrower: so play like 73 37 73",
        "annotation": []
    },
    {
        "text": "Gamethrower: if I die",
        "annotation": []
    },
    {
        "text": "Gamesolver: 4 try",
        "annotation": []
    },
    {
        "text": "Gamesolver: speeding up",
        "annotation": []
    },
    {
        "text": "Gamesolver: lol",
        "annotation": []
    },
    {
        "text": "MommyOrDaddy: I'm thinking ",
        "annotation": []
    },
    {
        "text": "Gamesolver: it doesnt matter who you shoot",
        "annotation": []
    },
    {
        "text": "Gamesolver: 1237 are all in line",
        "annotation": []
    },
    {
        "text": "Gamethrower: the tracker rly doesn't matter",
        "annotation": []
    },
    {
        "text": "Gamethrower: lol",
        "annotation": []
    },
    {
        "text": "Gamethrower: ok sure",
        "annotation": []
    },
    {
        "text": "Gamethrower: 13",
        "annotation": []
    },
    {
        "text": "sillylogic: so my pick between 4/7 was correct",
        "annotation": []
    },
    {
        "text": "Gamethrower: ye 2 wp",
        "annotation": []
    },
    {
        "text": "omichManiac: ye",
        "annotation": []
    },
    {
        "text": "MommyOrDaddy: 146 ",
        "annotation": []
    },
    {
        "text": "omichManiac: gj",
        "annotation": []
    },
    {
        "text": "Gamethrower: 13 31 ",
        "annotation": []
    },
    {
        "text": "Gamethrower: I think is best",
        "annotation": []
    },
    {
        "text": "Gamethrower: so we can skip 46 in this deck",
        "annotation": []
    },
    {
        "text": "Gamethrower: it should be super high wr",
        "annotation": []
    },
    {
        "text": "sillylogic: did 6 just afk?",
        "annotation": []
    },
    {
        "text": "Gamethrower: uh got rbb",
        "annotation": []
    },
    {
        "text": "Gamethrower: let me rethink",
        "annotation": []
    },
    {
        "text": "Gamethrower: might be better to go 21 32 now",
        "annotation": []
    },
    {
        "text": "Gamethrower: I think it is",
        "annotation": []
    },
    {
        "text": "Gamethrower: we get 79",
        "annotation": []
    },
    {
        "text": "Gamethrower: sad",
        "annotation": []
    },
    {
        "text": "Gamethrower: but it's only 2b in 6",
        "annotation": []
    },
    {
        "text": "Gamethrower: so we can't bank on rrb rrb",
        "annotation": []
    },
    {
        "text": "Gamethrower: so ja this",
        "annotation": []
    },
    {
        "text": "omichManiac: if 31 is rrr",
        "annotation": []
    },
    {
        "text": "omichManiac: we have 66%",
        "annotation": []
    },
    {
        "text": "Gamethrower: ye f 31 is rrr we just lose",
        "annotation": []
    },
    {
        "text": "omichManiac: on td",
        "annotation": []
    },
    {
        "text": "omichManiac: 2b in 3",
        "annotation": []
    },
    {
        "text": "Gamethrower: if 31 is rbb tho",
        "annotation": []
    },
    {
        "text": "Gamethrower: we just lose lol",
        "annotation": []
    },
    {
        "text": "Gamethrower: mostly",
        "annotation": []
    },
    {
        "text": "omichManiac: true",
        "annotation": []
    },
    {
        "text": "omichManiac: ja",
        "annotation": []
    },
    {
        "text": "Gamethrower: I think ja is better",
        "annotation": []
    },
    {
        "text": "Gamethrower: not too sure tbh",
        "annotation": []
    },
    {
        "text": "Gamethrower: 32",
        "annotation": []
    },
    {
        "text": "Gamethrower: have to ja this one too",
        "annotation": []
    },
    {
        "text": "Gamethrower: cuz of tracker",
        "annotation": []
    },
    {
        "text": "Gamethrower: so we get 79",
        "annotation": []
    },
    {
        "text": "Gamethrower: meh",
        "annotation": []
    },
    {
        "text": "MommyOrDaddy: I hope we win :pray: ",
        "annotation": []
    },
    {
        "text": "Gamethrower: you got 21%",
        "annotation": []
    },
    {
        "text": "Gamethrower: this is rrb then it's standard 79",
        "annotation": []
    },
    {
        "text": "MommyOrDaddy: 21 come in clutch pls",
        "annotation": [
            "Scarcity"
        ]
    },
    {
        "text": "omichManiac: imagine if 6 was hitler",
        "annotation": []
    },
    {
        "text": "omichManiac: tom",
        "annotation": []
    },
    {
        "text": "Gamethrower: XD I hope he is",
        "annotation": []
    },
    {
        "text": "FacismSux: I am",
        "annotation": []
    },
    {
        "text": "Gamethrower: and I shot 5 over him",
        "annotation": []
    },
    {
        "text": "Gamethrower: bruh",
        "annotation": []
    },
    {
        "text": "Gamethrower: wp to me",
        "annotation": []
    },
    {
        "text": "FacismSux: Rerun I sad I had to fo",
        "annotation": []
    },
    {
        "text": "FacismSux: u still shor 5",
        "annotation": []
    },
    {
        "text": "FacismSux: bruh",
        "annotation": []
    },
    {
        "text": "omichManiac: are u hitler for real",
        "annotation": []
    },
    {
        "text": "Gamethrower: I didn't think tht ameant u were hitler",
        "annotation": []
    },
    {
        "text": "Gamethrower: I did see that",
        "annotation": []
    },
    {
        "text": "sillylogic: i think 5 was more hitler than 6 to be honest",
        "annotation": []
    },
    {
        "text": "Gamethrower: I kinda thought ur trying to cover for 5",
        "annotation": []
    },
    {
        "text": "Gamethrower: being more hitler",
        "annotation": []
    },
    {
        "text": "Gamethrower: cuz people were scared of 136",
        "annotation": []
    },
    {
        "text": "Gamethrower: lol",
        "annotation": []
    },
    {
        "text": "Gamethrower: cuz 5 was outed too",
        "annotation": []
    },
    {
        "text": "Gamethrower: and I thought 5's more hitler",
        "annotation": []
    },
    {
        "text": "Gamethrower: ye but for hitler odds",
        "annotation": []
    },
    {
        "text": "Gamethrower: obv was wrong tho",
        "annotation": []
    },
    {
        "text": "omichManiac: hehehe",
        "annotation": []
    },
    {
        "text": "Gamethrower: xd we're losig too",
        "annotation": []
    },
    {
        "text": "Gamethrower: nice one",
        "annotation": []
    },
    {
        "text": "MommyOrDaddy: Omg ",
        "annotation": []
    },
    {
        "text": "MommyOrDaddy: W pray",
        "annotation": []
    },
    {
        "text": "Gamesolver: imagine we just shoot the outed fac",
        "annotation": []
    },
    {
        "text": "Gamesolver: xD",
        "annotation": []
    },
    {
        "text": "Gamesolver: kek",
        "annotation": []
    },
    {
        "text": "Gamethrower: xD",
        "annotation": []
    },
    {
        "text": "Gamethrower: good one by me",
        "annotation": []
    },
    {
        "text": "Gamesolver: even if hes reg",
        "annotation": []
    },
    {
        "text": "Gamesolver: u still give me some ease",
        "annotation": []
    },
    {
        "text": "Gamesolver: bc 5 is ",
        "annotation": []
    },
    {
        "text": "Gamesolver: green af",
        "annotation": []
    },
    {
        "text": "Gamethrower: sorry lol",
        "annotation": []
    },
    {
        "text": "Gamesolver: so he has \" some \" lib equity",
        "annotation": []
    },
    {
        "text": "Gamesolver: xd",
        "annotation": []
    },
    {
        "text": "Gamethrower: I took hitler shot",
        "annotation": []
    },
    {
        "text": "Gamethrower: and my conf was hitler",
        "annotation": []
    },
    {
        "text": "Gamethrower: XD",
        "annotation": []
    },
    {
        "text": "sillylogic: no remake?",
        "annotation": []
    },
    {
        "text": "omichManiac: manual ig",
        "annotation": []
    }
]